kanka_mcp.py
mseep_kanka_mcp-0.1.1.dist-info/licenses/LICENSE
mseep_kanka_mcp-0.1.1.dist-info/METADATA
mseep_kanka_mcp-0.1.1.dist-info/WHEEL
mseep_kanka_mcp-0.1.1.dist-info/entry_points.txt
mseep_kanka_mcp-0.1.1.dist-info/top_level.txt
mseep_kanka_mcp-0.1.1.dist-info/RECORD
