Metadata-Version: 2.4
Name: mseep-kanka-mcp
Version: 0.1.1
Summary: A MCP Server interacting with Kanka Campaigns
Author-email: mseep <support@skydeck.ai>
Requires-Python: >=3.13
License-File: LICENSE
Requires-Dist: mcp[cli]>=1.6.0
Requires-Dist: requests>=2.32.3
Dynamic: license-file
